{
    "odds": [
        25,
        25,
        25,
        25
    ],
    "categories": {
        "stat_quartz": [
            "Defense 1",
            "Break 1",
            "HP 1",
            "Shield 1",
            "Attack 1",
            "Strike 1",
            "Evade 1",
            "Move 1",
            "Action 1",
            "Cast 1",
            "EP Cut 1",
            "Hit 1",
            "Impede 1",
            "EP 1",
            "Mind 1"
        ],
        "aliment_quartz": [
            "Poison",
            "Petrify",
            "Shield Breaker",
            "Mute",
            "Freeze",
            "Spirit Breaker",
            "Seal",
            "Burn",
            "Sword Breaker",
            "Blind",
            "Sleep",
            "Leg Breaker",
            "Nightmare",
            "Speed Breaker",
            "Faint",
            "Confuse",
            "Voice Breaker"
        ],
        "art_quartz": [
            "Needle Shoot R",
            "Ivy Nail R",
            "Crest R",
            "Crest SR",
            "La Crest R",
            "Earth Pulse R",
            "Aqua Bleed R",
            "Crystal Edge R",
            "Curia R",
            "Curia SR",
            "Tear R",
            "Thelas R",
            "Fire Bolt R",
            "Venom Flame R",
            "Forte R",
            "Forte SR",
            "La Forte R",
            "Heat Up R",
            "Impassion R",
            "Impassion SR",
            "Air Strike R",
            "Nemesis Arrow R",
            "Breath R",
            "Recuria R",
            "Soul Blur R",
            "Chrono Drive R",
            "Chrono Break R",
            "Golden Sphere R",
            "Fortuna R",
            "Shining R",
            "Silver Thorn R",
            "Analyze R",
            "Analyze SR",
            "Saintly Force R",
            "Crescent Mirror R"
        ],
        "others": [
            "Black Zemurian Ore",
            "Zeram Powder",
            "Brave Seed",
            "Gladiator Headband",
            "Gladiator Belt",
            "Silver Earring",
            "Coral Ring",
            "Marble Ring",
            "White Glasses",
            "Black Bangle",
            "Cool Necklace",
            "Lighter",
            "Stone Brooch",
            "Citrus Bottle",
            "Floral Bottle",
            "Holy Chain",
            "Force Seal",
            "Leather Watch"
        ]
    }
}